{
  "type": "NTR",
  "characters": [
    {
      "name": "佐藤悠真",
      "age": 29,
      "physical_features": "身長180cm、細身だが筋肉質、黒髪短髪、鋭い目つき",
      "personality": "真面目で責任感が強いが、恋愛には奥手。嫉妬心を内に秘めるタイプ"
    },
    {
      "name": "高橋美咲",
      "age": 27,
      "physical_features": "身長165cm、華奢な体型、長い栗色の髪、優しげな目元",
      "personality": "明るく人懐っこい性格だが、流されやすく心の奥底で刺激を求める一面を持つ"
    },
    {
      "name": "中村翔",
      "age": 32,
      "physical_features": "身長185cm、がっしりとした体格、短い金髪、自信に満ちた笑顔",
      "personality": "自信家で大胆、口が上手く女性を惹きつける魅力を持つが、自己中心的な一面も"
    },
    {
      "name": "田中彩花",
      "age": 25,
      "physical_features": "身長160cm、ふくよかな体型、黒髪ボブ、眼鏡をかけた知的な印象",
      "personality": "内向的で観察力があり、人の感情の機微に敏感。秘密を抱えている"
    }
  ],
  "setting": {
    "location": "日本の地方都市にある小さなアパートとその周辺の温泉旅館",
    "era": "現代（2023年）"
  },
  "background": {
    "relationship": "佐藤悠真と高橋美咲は大学時代からの恋人で、結婚を前提に同棲中。悠真は仕事で多忙な日々を送り、美咲は寂しさを感じ始めている。そんな中、悠真の大学時代の先輩である中村翔が地元に帰省し、偶然再会。翔は美咲に興味を持ち、巧みに距離を縮めていく。田中彩花は美咲の親友で、彼女の揺れる心を察しながらも、ある秘密を胸に秘め、事態を見守る。舞台となる温泉旅館は、翔が美咲を誘う口実として計画した週末旅行の場所であり、そこで関係が大きく動き始める。"
  }
}